MANIFEST.in
README.rst
cttsmodule.c
setup.cfg
setup.py
ttspico.py
picopi/pico/lang/de-DE_gl0_sg.bin
picopi/pico/lang/de-DE_ta.bin
picopi/pico/lang/en-GB_kh0_sg.bin
picopi/pico/lang/en-GB_ta.bin
picopi/pico/lang/en-US_lh0_sg.bin
picopi/pico/lang/en-US_ta.bin
picopi/pico/lang/es-ES_ta.bin
picopi/pico/lang/es-ES_zl0_sg.bin
picopi/pico/lang/fr-FR_nk0_sg.bin
picopi/pico/lang/fr-FR_ta.bin
picopi/pico/lang/it-IT_cm0_sg.bin
picopi/pico/lang/it-IT_ta.bin
picopi/pico/lib/Android.mk
picopi/pico/lib/MODULE_LICENSE_APACHE2
picopi/pico/lib/Makefile
picopi/pico/lib/NOTICE
picopi/pico/lib/picoacph.c
picopi/pico/lib/picoacph.h
picopi/pico/lib/picoapi.c
picopi/pico/lib/picoapi.h
picopi/pico/lib/picoapid.h
picopi/pico/lib/picobase.c
picopi/pico/lib/picobase.h
picopi/pico/lib/picocep.c
picopi/pico/lib/picocep.h
picopi/pico/lib/picoctrl.c
picopi/pico/lib/picoctrl.h
picopi/pico/lib/picodata.c
picopi/pico/lib/picodata.h
picopi/pico/lib/picodbg.c
picopi/pico/lib/picodbg.h
picopi/pico/lib/picodefs.h
picopi/pico/lib/picodsp.h
picopi/pico/lib/picoextapi.c
picopi/pico/lib/picoextapi.h
picopi/pico/lib/picofftsg.c
picopi/pico/lib/picofftsg.h
picopi/pico/lib/picokdbg.c
picopi/pico/lib/picokdbg.h
picopi/pico/lib/picokdt.c
picopi/pico/lib/picokdt.h
picopi/pico/lib/picokfst.c
picopi/pico/lib/picokfst.h
picopi/pico/lib/picoklex.c
picopi/pico/lib/picoklex.h
picopi/pico/lib/picoknow.c
picopi/pico/lib/picoknow.h
picopi/pico/lib/picokpdf.c
picopi/pico/lib/picokpdf.h
picopi/pico/lib/picokpr.c
picopi/pico/lib/picokpr.h
picopi/pico/lib/picoktab.c
picopi/pico/lib/picoktab.h
picopi/pico/lib/picoos.c
picopi/pico/lib/picoos.h
picopi/pico/lib/picopal.c
picopi/pico/lib/picopal.h
picopi/pico/lib/picopam.c
picopi/pico/lib/picopam.h
picopi/pico/lib/picopltf.h
picopi/pico/lib/picopr.c
picopi/pico/lib/picopr.h
picopi/pico/lib/picorsrc.c
picopi/pico/lib/picorsrc.h
picopi/pico/lib/picosa.c
picopi/pico/lib/picosa.h
picopi/pico/lib/picosig.c
picopi/pico/lib/picosig.h
picopi/pico/lib/picosig2.c
picopi/pico/lib/picosig2.h
ttspico.egg-info/PKG-INFO
ttspico.egg-info/SOURCES.txt
ttspico.egg-info/dependency_links.txt
ttspico.egg-info/entry_points.txt
ttspico.egg-info/namespace_packages.txt
ttspico.egg-info/not-zip-safe
ttspico.egg-info/requires.txt
ttspico.egg-info/top_level.txt