Metadata-Version: 1.1
Name: ttspico
Version: 0.3.2
Summary: Python simple text to speech module.
Home-page: http://github.com/sevangelatos/py-ttspico
Author: Spiros Evangelatos
Author-email: sevangelatos@gmail.com
License: Apache License 2.0
Keywords: speech text-to-speech svox
Platform: UNKNOWN
Classifier: Programming Language :: Python
Classifier: Development Status :: 3 - Alpha
Classifier: Topic :: Multimedia :: Sound/Audio :: Speech
Classifier: Environment :: Console
Classifier: Intended Audience :: Developers
Classifier: Operating System :: POSIX
Classifier: License :: OSI Approved :: Apache Software License
